<arguments>
	<argument>
		<name>length</name>
		<type>float</type>
		<description>length of the box</description>
	</argument>
	
	<argument>
		<name>width</name>
		<type>float</type>
		<description>width of the box</description>
	</argument>
	
	<argument>
		<name>height</name>
		<type>float</type>
		<description>height of the box</description>
	</argument>
	
	<optionalArgument>
		<name>--help</name>
		<numValues>0</numValues>
		<type></type>
		<description>help center</description>
		<value></value>
		<shortName>-h</shortName>
	</optionalArgument>
	
	<optionalArgument>
		<name>--type</name>
		<numValues>1</numValues>
		<type>string</type>
		<description>Type of shape</description>
		<value>box</value>
		<shortName>-t</shortName>
	</optionalArgument>
	
</arguments>